pyhip/__init__.py
pyhip/cli.py
pyhip/hip_Darwin
pyhip/hip_Darwin.exe
pyhip/hip_Linux.exe
pyhip/hip_wrapper.pyx
pyhip/hipster.py
pyhip/batch/adapt.yml
pyhip/batch/basic.yml
pyhip/batch/batch.py
pyhip/batch/complete.yml
pyhip/batch/interpolation.yml
pyhip/commands/__init__.py
pyhip/commands/mesh_idcard.py
pyhip/commands/operations.py
pyhip/commands/readers.py
pyhip/commands/writers.py
pyhip/gui/engine_3d_input.py
pyhip/gui/engine_3d_interpolate.py
pyhip/gui/engine_3d_output.py
pyhip/gui/hip.yaml
pyhip/gui/parser_utils.py
pyhip/gui/process_finish.py
pyhip/gui/process_inputs.py
pyhip/gui/process_interpolate.py
pyhip/gui/startup.py
pyhip/gui/pictures/Periodic_axi_200.gif
pyhip/gui/pictures/adaptation.png
pyhip/gui/pictures/adaptation_2d.png
pyhip/gui/pictures/interpolation.png
pyhip/gui/pictures/mesh_banderole.png
pyhip/gui/pictures/set_perio.gif
pyhip/scenarii/__init__.py
pyhip/scenarii/adaptation.py
pyhip/scenarii/basic.py
pyhip/scenarii/complete.py
pyhip/scenarii/interpolation.py
pyhip/setup/__init__.py
pyhip/setup/core.py
pyhip/setup/optionals.py
pyhip-1.3.1.dist-info/METADATA
pyhip-1.3.1.dist-info/WHEEL
pyhip-1.3.1.dist-info/entry_points.txt
pyhip-1.3.1.dist-info/top_level.txt
pyhip-1.3.1.dist-info/RECORD
