Metadata-Version: 2.4
Name: pyhip
Version: 1.3.1
Summary: A Python interface to Hip for manipulating unstructured computational grids
Home-page: http://www.cerfacs.fr/avbp7x/hip.php
Author: Jens-Dominik Mueller, CERFACS
Author-email: j.mueller@qmul.ac.uk, gabriel.staffelbach@cerfacs.fr, erraiya@cerfacs.fr
License: CeCILL-B Free Software License Agreement (CECILL-B)
Classifier: Development Status :: 4 - Beta
Classifier: Programming Language :: Python :: 3.9
Classifier: Programming Language :: Python :: 3.10
Classifier: Programming Language :: Python :: 3.11
Classifier: Programming Language :: Python :: 3.12
Classifier: Programming Language :: Python :: 3.13
Classifier: Programming Language :: Python :: 3.14
Classifier: Topic :: Scientific/Engineering :: Physics
Requires-Python: >=3.9.0
Requires-Dist: numpy
Requires-Dist: nob
Requires-Dist: reportlab
Requires-Dist: PyYAML
Requires-Dist: matplotlib
Requires-Dist: scipy
Requires-Dist: arnica
Requires-Dist: opentea>=3.1.0
Dynamic: author
Dynamic: author-email
Dynamic: classifier
Dynamic: description
Dynamic: description-content-type
Dynamic: home-page
Dynamic: license
Dynamic: requires-dist
Dynamic: requires-python
Dynamic: summary
